CHANGELOG.txt
LICENSE.txt
MANIFEST.in
README.md
setup.py
tests.py
hamming/__init__.py
hamming/hammingcode.py
hamming.egg-info/PKG-INFO
hamming.egg-info/SOURCES.txt
hamming.egg-info/dependency_links.txt
hamming.egg-info/top_level.txt