Metadata-Version: 1.1
Name: hamming
Version: 0.0.4
Summary: Hamming code generation and error detection
Home-page: UNKNOWN
Author: Ambuj Dubey
Author-email: ambujdubey2426@gmail.com
License: UNKNOWN
Keywords: hamming code
Platform: UNKNOWN
Classifier: Development Status :: 5 - Production/Stable
Classifier: Intended Audience :: Education
Classifier: Operating System :: Microsoft :: Windows :: Windows 8
Classifier: License :: OSI Approved :: MIT License
Classifier: Programming Language :: Python :: 3
